Metadata-Version: 2.1
Name: gitlab-gce-autoscaler
Version: 0.1.2
Summary: Very simple autoscaler for GCE instance groups & GitLab CI
Home-page: https://github.com/brndnmtthws/gitlab-gce-autoscaler
Author: Brenden Matthews
Author-email: brenden@diddyinc.com
License: UNKNOWN
Platform: UNKNOWN
Classifier: Programming Language :: Python :: 3
Classifier: License :: OSI Approved :: Apache Software License
Classifier: Operating System :: OS Independent
Requires-Python: >=3.5
